pycrea/__init__.py
pycrea/crea.py
pycrea-0.1.3.dist-info/METADATA
pycrea-0.1.3.dist-info/WHEEL
pycrea-0.1.3.dist-info/top_level.txt
pycrea-0.1.3.dist-info/RECORD
