Metadata-Version: 2.4
Name: pycrea
Version: 0.1.3
Summary: A Python package to parse and manage CREA word vectors. Learn more about this project on GitHub: https://github.com/WiredBrains-Lab/
Home-page: https://github.com/askitowski1/CREA-Vectors/tree/main/crea_library
Author: Alex Skitowski
Author-email: Alex Skitowski <askitowski@mcw.edu>
License: MIT
Requires-Dist: numpy
Requires-Dist: scikit-learn
Requires-Dist: scipy
Requires-Dist: pandas
Dynamic: author
Dynamic: home-page
